sideseeing_tools/__init__.py
sideseeing_tools/constants.py
sideseeing_tools/exceptions.py
sideseeing_tools/media.py
sideseeing_tools/plot.py
sideseeing_tools/sideseeing.py
sideseeing_tools/utils.py
sideseeing_tools-0.9.1.dist-info/LICENSE
sideseeing_tools-0.9.1.dist-info/METADATA
sideseeing_tools-0.9.1.dist-info/WHEEL
sideseeing_tools-0.9.1.dist-info/top_level.txt
sideseeing_tools-0.9.1.dist-info/RECORD
