Metadata-Version: 2.1
Name: sideseeing-tools
Version: 0.9.1
Summary: A set of tools to load, preprocess and analyze data collected through the MultiSensor Data Collection App
Author-email: "Rafael J. P. Damaceno" <rafael.damaceno@ime.usp.br>
Project-URL: Homepage, https://github.com/rafaelpezzuto/sideseeing-tools
Project-URL: Issues, https://github.com/rafaelpezzuto/sideseeing-tools/issues
Classifier: Programming Language :: Python :: 3
Classifier: License :: OSI Approved :: MIT License
Classifier: Operating System :: OS Independent
Requires-Python: >=3.9
License-File: LICENSE
Requires-Dist: decorator
Requires-Dist: folium
Requires-Dist: imageio
Requires-Dist: librosa
Requires-Dist: matplotlib
Requires-Dist: moviepy >=2.0.0
Requires-Dist: numpy
Requires-Dist: opencv-python
Requires-Dist: pandas
Requires-Dist: reverse-geocode
Provides-Extra: dev
Requires-Dist: pytest ; extra == 'dev'
